{
  "meta": {
    "amc": "Franklin Mutual Fund",
    "total_schemes": 23
  },
  "schemes": {
    "franklin-asian-equity-fund-g": {
      "name": "Franklin Asian Equity Fund(G)",
      "category": "EQ-INTL",
      "nav": 38.17,
      "nav_date": "02 Feb 2026",
      "expense_ratio": "",
      "benchmark": "",
      "returns": {
        "1Y": "",
        "3Y": "",
        "5Y": ""
      },
      "invest_url": ""
    },
    "franklin-build-india-fund-g": {
      "name": "Franklin Build India Fund(G)",
      "category": "EQ-INFRA",
      "nav": 140.08,
      "nav_date": "02 Feb 2026",
      "expense_ratio": "",
      "benchmark": "",
      "returns": {
        "1Y": "",
        "3Y": "",
        "5Y": ""
      },
      "invest_url": ""
    },
    "franklin-india-aggressive-hybrid-fund-g": {
      "name": "Franklin India Aggressive Hybrid Fund(G)",
      "category": "HY-EQ",
      "nav": 267.69,
      "nav_date": "02 Feb 2026",
      "expense_ratio": "",
      "benchmark": "",
      "returns": {
        "1Y": "",
        "3Y": "",
        "5Y": ""
      },
      "invest_url": ""
    },
    "franklin-india-arbitrage-fund-reg-g": {
      "name": "Franklin India Arbitrage Fund-Reg(G)",
      "category": "HY-ARB",
      "nav": 10.78,
      "nav_date": "02 Feb 2026",
      "expense_ratio": "",
      "benchmark": "",
      "returns": {
        "1Y": "",
        "3Y": "",
        "5Y": ""
      },
      "invest_url": ""
    },
    "franklin-india-balanced-advantage-fund-reg-g": {
      "name": "Franklin India Balanced Advantage Fund-Reg(G)",
      "category": "HY-DYN",
      "nav": 14.34,
      "nav_date": "02 Feb 2026",
      "expense_ratio": "",
      "benchmark": "",
      "returns": {
        "1Y": "",
        "3Y": "",
        "5Y": ""
      },
      "invest_url": ""
    },
    "franklin-india-dividend-yield-fund-g": {
      "name": "Franklin India Dividend Yield Fund(G)",
      "category": "EQ-DIV",
      "nav": 139.47,
      "nav_date": "02 Feb 2026",
      "expense_ratio": "",
      "benchmark": "",
      "returns": {
        "1Y": "",
        "3Y": "",
        "5Y": ""
      },
      "invest_url": ""
    },
    "franklin-india-dynamic-asset-allocation-active-fofs-g": {
      "name": "Franklin India Dynamic Asset Allocation Active FOFs(G)",
      "category": "FOF-DOM",
      "nav": 164.04,
      "nav_date": "02 Feb 2026",
      "expense_ratio": "",
      "benchmark": "",
      "returns": {
        "1Y": "",
        "3Y": "",
        "5Y": ""
      },
      "invest_url": ""
    },
    "franklin-india-elss-tax-saver-fund-g": {
      "name": "Franklin India ELSS Tax Saver Fund(G)",
      "category": "EQ-ELSS",
      "nav": 1446.14,
      "nav_date": "02 Feb 2026",
      "expense_ratio": "",
      "benchmark": "",
      "returns": {
        "1Y": "",
        "3Y": "",
        "5Y": ""
      },
      "invest_url": ""
    },
    "franklin-india-equity-savings-fund-g": {
      "name": "Franklin India Equity Savings Fund(G)",
      "category": "HY-EQ",
      "nav": 16.75,
      "nav_date": "02 Feb 2026",
      "expense_ratio": "",
      "benchmark": "",
      "returns": {
        "1Y": "",
        "3Y": "",
        "5Y": ""
      },
      "invest_url": ""
    },
    "franklin-india-flexi-cap-fund-g": {
      "name": "Franklin India Flexi Cap Fund(G)",
      "category": "EQ-FLEX",
      "nav": 1615.64,
      "nav_date": "02 Feb 2026",
      "expense_ratio": "",
      "benchmark": "",
      "returns": {
        "1Y": "",
        "3Y": "",
        "5Y": ""
      },
      "invest_url": ""
    },
    "franklin-india-focused-equity-fund-g": {
      "name": "Franklin India Focused Equity Fund(G)",
      "category": "EQ-MLC",
      "nav": 106.96,
      "nav_date": "02 Feb 2026",
      "expense_ratio": "",
      "benchmark": "",
      "returns": {
        "1Y": "",
        "3Y": "",
        "5Y": ""
      },
      "invest_url": ""
    },
    "franklin-india-income-plus-arbitrage-active-fof-g": {
      "name": "Franklin India Income Plus Arbitrage Active FoF(G)",
      "category": "FOF-DOM",
      "nav": 21.62,
      "nav_date": "02 Feb 2026",
      "expense_ratio": "",
      "benchmark": "",
      "returns": {
        "1Y": "",
        "3Y": "",
        "5Y": ""
      },
      "invest_url": ""
    },
    "franklin-india-large-mid-cap-fund-g": {
      "name": "Franklin India Large & Mid Cap Fund(G)",
      "category": "EQ-L&M",
      "nav": 187.17,
      "nav_date": "02 Feb 2026",
      "expense_ratio": "",
      "benchmark": "",
      "returns": {
        "1Y": "",
        "3Y": "",
        "5Y": ""
      },
      "invest_url": ""
    },
    "franklin-india-large-cap-fund-g": {
      "name": "Franklin India Large Cap Fund(G)",
      "category": "EQ-LC",
      "nav": 1029.9,
      "nav_date": "02 Feb 2026",
      "expense_ratio": "",
      "benchmark": "",
      "returns": {
        "1Y": "",
        "3Y": "",
        "5Y": ""
      },
      "invest_url": ""
    },
    "franklin-india-mid-cap-fund-g": {
      "name": "Franklin India Mid Cap Fund(G)",
      "category": "EQ-MID",
      "nav": 2672.07,
      "nav_date": "02 Feb 2026",
      "expense_ratio": "",
      "benchmark": "",
      "returns": {
        "1Y": "",
        "3Y": "",
        "5Y": ""
      },
      "invest_url": ""
    },
    "franklin-india-multi-asset-allocation-fund-reg-g": {
      "name": "Franklin India Multi Asset Allocation Fund-Reg(G)",
      "category": "HY-MULTI",
      "nav": 11.21,
      "nav_date": "02 Feb 2026",
      "expense_ratio": "",
      "benchmark": "",
      "returns": {
        "1Y": "",
        "3Y": "",
        "5Y": ""
      },
      "invest_url": ""
    },
    "franklin-india-multi-cap-fund-reg-g": {
      "name": "Franklin India Multi Cap Fund-Reg(G)",
      "category": "EQ-MLC",
      "nav": 10.22,
      "nav_date": "02 Feb 2026",
      "expense_ratio": "",
      "benchmark": "",
      "returns": {
        "1Y": "",
        "3Y": "",
        "5Y": ""
      },
      "invest_url": ""
    },
    "franklin-india-multi-factor-fund-g": {
      "name": "Franklin India Multi-Factor Fund(G)",
      "category": "EQ-THEM",
      "nav": 9.79,
      "nav_date": "02 Feb 2026",
      "expense_ratio": "",
      "benchmark": "",
      "returns": {
        "1Y": "",
        "3Y": "",
        "5Y": ""
      },
      "invest_url": ""
    },
    "franklin-india-nse-nifty-50-index-fund-g": {
      "name": "Franklin India NSE Nifty 50 Index Fund(G)",
      "category": "EQ-INDX",
      "nav": 204.66,
      "nav_date": "02 Feb 2026",
      "expense_ratio": "",
      "benchmark": "",
      "returns": {
        "1Y": "",
        "3Y": "",
        "5Y": ""
      },
      "invest_url": ""
    },
    "franklin-india-opportunities-fund-g": {
      "name": "Franklin India Opportunities Fund(G)",
      "category": "EQ-THEM",
      "nav": 248.36,
      "nav_date": "02 Feb 2026",
      "expense_ratio": "",
      "benchmark": "",
      "returns": {
        "1Y": "",
        "3Y": "",
        "5Y": ""
      },
      "invest_url": ""
    },
    "franklin-india-small-cap-fund-g": {
      "name": "Franklin India Small Cap Fund(G)",
      "category": "EQ-SML",
      "nav": 156.83,
      "nav_date": "02 Feb 2026",
      "expense_ratio": "",
      "benchmark": "",
      "returns": {
        "1Y": "",
        "3Y": "",
        "5Y": ""
      },
      "invest_url": ""
    },
    "franklin-india-technology-fund-g": {
      "name": "Franklin India Technology Fund(G)",
      "category": "EQ-TECH",
      "nav": 523.36,
      "nav_date": "02 Feb 2026",
      "expense_ratio": "",
      "benchmark": "",
      "returns": {
        "1Y": "",
        "3Y": "",
        "5Y": ""
      },
      "invest_url": ""
    },
    "franklin-u-s-opportunities-equity-active-fof-g": {
      "name": "Franklin U.S. Opportunities Equity Active FOF(G)",
      "category": "FOF-OVR",
      "nav": 83.16,
      "nav_date": "02 Feb 2026",
      "expense_ratio": "",
      "benchmark": "",
      "returns": {
        "1Y": "",
        "3Y": "",
        "5Y": ""
      },
      "invest_url": ""
    }
  }
}