{
  "amc_name": "NIPPON INDIA MUTUAL FUND",
  "schemes": {
    "nippon-india-active-momentum-fund-review-performance-risk-explained-simply/": {
      "name": "Nippon India Active Momentum Fund-Reg(G)",
      "category": "",
      "nav": "",
      "nav_date": "",
      "returns": {},
      "allocation": {},
      "risk_level": "",
      "risk_quants": {},
      "benchmark": "",
      "expense_ratio": ""
    },
    "nippon-india-aggressive-hybrid-fund-review-performance-risk-explained-simply/": {
      "name": "Nippon India Aggressive Hybrid Fund(G)",
      "category": "",
      "nav": "",
      "nav_date": "",
      "returns": {},
      "allocation": {},
      "risk_level": "",
      "risk_quants": {},
      "benchmark": "",
      "expense_ratio": ""
    },
    "nippon-india-arbitrage-fund-review-performance-risk-explained-simply/": {
      "name": "Nippon India Arbitrage Fund(G)",
      "category": "",
      "nav": "",
      "nav_date": "",
      "returns": {},
      "allocation": {},
      "risk_level": "",
      "risk_quants": {},
      "benchmark": "",
      "expense_ratio": ""
    },
    "nippon-india-balanced-advantage-fund-review-performance-risk-explained-simply/": {
      "name": "Nippon India Balanced Advantage Fund(G)",
      "category": "",
      "nav": "",
      "nav_date": "",
      "returns": {},
      "allocation": {},
      "risk_level": "",
      "risk_quants": {},
      "benchmark": "",
      "expense_ratio": ""
    },
    "nippon-india-banking-financial-services-fund-review-performance-risk-explained-simply/": {
      "name": "Nippon India Banking & Financial Services Fund(G)",
      "category": "",
      "nav": "",
      "nav_date": "",
      "returns": {},
      "allocation": {},
      "risk_level": "",
      "risk_quants": {},
      "benchmark": "",
      "expense_ratio": ""
    },
    "nippon-india-bse-sensex-next-30-index-fund-review-performance-risk-explained-simply/": {
      "name": "Nippon India BSE Sensex Next 30 Index Fund-Reg(G)",
      "category": "",
      "nav": "",
      "nav_date": "",
      "returns": {},
      "allocation": {},
      "risk_level": "",
      "risk_quants": {},
      "benchmark": "",
      "expense_ratio": ""
    },
    "nippon-india-consumption-fund-review-performance-risk-explained-simply/": {
      "name": "Nippon India Consumption Fund(G)",
      "category": "",
      "nav": "",
      "nav_date": "",
      "returns": {},
      "allocation": {},
      "risk_level": "",
      "risk_quants": {},
      "benchmark": "",
      "expense_ratio": ""
    },
    "nippon-india-diversified-equity-flexicap-passive-fof-review-performance-risk-explained-simply/": {
      "name": "Nippon India Diversified Equity Flexicap Passive FoF-Reg(G)",
      "category": "",
      "nav": "",
      "nav_date": "",
      "returns": {},
      "allocation": {},
      "risk_level": "",
      "risk_quants": {},
      "benchmark": "",
      "expense_ratio": ""
    },
    "nippon-india-elss-tax-saver-fund-review-performance-risk-explained-simply/": {
      "name": "Nippon India ELSS Tax Saver Fund(G)",
      "category": "",
      "nav": "",
      "nav_date": "",
      "returns": {},
      "allocation": {},
      "risk_level": "",
      "risk_quants": {},
      "benchmark": "",
      "expense_ratio": ""
    },
    "nippon-india-equity-savings-fund-review-performance-risk-explained-simply/": {
      "name": "Nippon India Equity Savings Fund(G)",
      "category": "",
      "nav": "",
      "nav_date": "",
      "returns": {},
      "allocation": {},
      "risk_level": "",
      "risk_quants": {},
      "benchmark": "",
      "expense_ratio": ""
    },
    "nippon-india-flexi-cap-fund-review-performance-risk-explained-simply/": {
      "name": "Nippon India Flexi Cap Fund-Reg(G)",
      "category": "",
      "nav": "",
      "nav_date": "",
      "returns": {},
      "allocation": {},
      "risk_level": "",
      "risk_quants": {},
      "benchmark": "",
      "expense_ratio": ""
    },
    "nippon-india-focused-fund-review-performance-risk-explained-simply/": {
      "name": "Nippon India Focused Fund(G)",
      "category": "",
      "nav": "",
      "nav_date": "",
      "returns": {},
      "allocation": {},
      "risk_level": "",
      "risk_quants": {},
      "benchmark": "",
      "expense_ratio": ""
    },
    "nippon-india-gold-savings-fund-review-performance-risk-explained-simply/": {
      "name": "Nippon India Gold Savings Fund(G)",
      "category": "",
      "nav": "",
      "nav_date": "",
      "returns": {},
      "allocation": {},
      "risk_level": "",
      "risk_quants": {},
      "benchmark": "",
      "expense_ratio": ""
    },
    "nippon-india-growth-mid-cap-fund-review-performance-risk-explained-simply/": {
      "name": "Nippon India Growth Mid Cap Fund(G)",
      "category": "",
      "nav": "",
      "nav_date": "",
      "returns": {},
      "allocation": {},
      "risk_level": "",
      "risk_quants": {},
      "benchmark": "",
      "expense_ratio": ""
    },
    "nippon-india-income-plus-arbitrage-active-fof-review-performance-risk-explained-simply/": {
      "name": "Nippon India Income Plus Arbitrage Active FoF-Reg(G)",
      "category": "",
      "nav": "",
      "nav_date": "",
      "returns": {},
      "allocation": {},
      "risk_level": "",
      "risk_quants": {},
      "benchmark": "",
      "expense_ratio": ""
    },
    "nippon-india-index-fund-bse-sensex-plan-review-performance-risk-explained-simply/": {
      "name": "Nippon India Index Fund-BSE Sensex Plan(G)",
      "category": "",
      "nav": "",
      "nav_date": "",
      "returns": {},
      "allocation": {},
      "risk_level": "",
      "risk_quants": {},
      "benchmark": "",
      "expense_ratio": ""
    },
    "nippon-india-index-fund-nifty-50-plan-review-performance-risk-explained-simply/": {
      "name": "Nippon India Index Fund-Nifty 50 Plan(G)",
      "category": "",
      "nav": "",
      "nav_date": "",
      "returns": {},
      "allocation": {},
      "risk_level": "",
      "risk_quants": {},
      "benchmark": "",
      "expense_ratio": ""
    },
    "nippon-india-innovation-fund-review-performance-risk-explained-simply/": {
      "name": "Nippon India Innovation Fund-Reg(G)",
      "category": "",
      "nav": "",
      "nav_date": "",
      "returns": {},
      "allocation": {},
      "risk_level": "",
      "risk_quants": {},
      "benchmark": "",
      "expense_ratio": ""
    },
    "nippon-india-japan-equity-fund-review-performance-risk-explained-simply/": {
      "name": "Nippon India Japan Equity Fund(G)",
      "category": "",
      "nav": "",
      "nav_date": "",
      "returns": {},
      "allocation": {},
      "risk_level": "",
      "risk_quants": {},
      "benchmark": "",
      "expense_ratio": ""
    },
    "nippon-india-large-cap-fund-review-performance-risk-explained-simply/": {
      "name": "Nippon India Large Cap Fund(G)",
      "category": "",
      "nav": "",
      "nav_date": "",
      "returns": {},
      "allocation": {},
      "risk_level": "",
      "risk_quants": {},
      "benchmark": "",
      "expense_ratio": ""
    },
    "nippon-india-mnc-fund-review-performance-risk-explained-simply/": {
      "name": "Nippon India MNC Fund-Reg(G)",
      "category": "",
      "nav": "",
      "nav_date": "",
      "returns": {},
      "allocation": {},
      "risk_level": "",
      "risk_quants": {},
      "benchmark": "",
      "expense_ratio": ""
    },
    "nippon-india-multi-asset-allocation-fund-review-performance-risk-explained-simply/": {
      "name": "Nippon India Multi Asset Allocation Fund-Reg(G)",
      "category": "",
      "nav": "",
      "nav_date": "",
      "returns": {},
      "allocation": {},
      "risk_level": "",
      "risk_quants": {},
      "benchmark": "",
      "expense_ratio": ""
    },
    "nippon-india-multi-cap-fund-review-performance-risk-explained-simply/": {
      "name": "Nippon India Multi Cap Fund(G)",
      "category": "",
      "nav": "",
      "nav_date": "",
      "returns": {},
      "allocation": {},
      "risk_level": "",
      "risk_quants": {},
      "benchmark": "",
      "expense_ratio": ""
    },
    "nippon-india-multi-asset-omni-fof-review-performance-risk-explained-simply/": {
      "name": "Nippon India Multi-Asset Omni FoF-Reg(G)",
      "category": "",
      "nav": "",
      "nav_date": "",
      "returns": {},
      "allocation": {},
      "risk_level": "",
      "risk_quants": {},
      "benchmark": "",
      "expense_ratio": ""
    },
    "nippon-india-nifty-50-value-20-index-fund-review-performance-risk-explained-simply/": {
      "name": "Nippon India Nifty 50 Value 20 Index Fund-Reg(G)",
      "category": "",
      "nav": "",
      "nav_date": "",
      "returns": {},
      "allocation": {},
      "risk_level": "",
      "risk_quants": {},
      "benchmark": "",
      "expense_ratio": ""
    },
    "nippon-india-nifty-500-equal-weight-index-fund-review-performance-risk-explained-simply/": {
      "name": "Nippon India Nifty 500 Equal Weight Index Fund-Reg(G)",
      "category": "",
      "nav": "",
      "nav_date": "",
      "returns": {},
      "allocation": {},
      "risk_level": "",
      "risk_quants": {},
      "benchmark": "",
      "expense_ratio": ""
    },
    "nippon-india-nifty-500-low-volatility-50-index-fund-review-performance-risk-explained-simply/": {
      "name": "Nippon India Nifty 500 Low Volatility 50 Index Fund-Reg(G)",
      "category": "",
      "nav": "",
      "nav_date": "",
      "returns": {},
      "allocation": {},
      "risk_level": "",
      "risk_quants": {},
      "benchmark": "",
      "expense_ratio": ""
    },
    "nippon-india-nifty-500-momentum-50-index-fund-review-performance-risk-explained-simply/": {
      "name": "Nippon India Nifty 500 Momentum 50 Index Fund-Reg(G)",
      "category": "",
      "nav": "",
      "nav_date": "",
      "returns": {},
      "allocation": {},
      "risk_level": "",
      "risk_quants": {},
      "benchmark": "",
      "expense_ratio": ""
    },
    "nippon-india-nifty-500-quality-50-index-fund-review-performance-risk-explained-simply/": {
      "name": "Nippon India Nifty 500 Quality 50 Index Fund-Reg(G)",
      "category": "",
      "nav": "",
      "nav_date": "",
      "returns": {},
      "allocation": {},
      "risk_level": "",
      "risk_quants": {},
      "benchmark": "",
      "expense_ratio": ""
    },
    "nippon-india-nifty-alpha-low-volatility-30-index-fund-review-performance-risk-explained-simply/": {
      "name": "Nippon India Nifty Alpha Low Volatility 30 Index Fund(G)",
      "category": "",
      "nav": "",
      "nav_date": "",
      "returns": {},
      "allocation": {},
      "risk_level": "",
      "risk_quants": {},
      "benchmark": "",
      "expense_ratio": ""
    },
    "nippon-india-nifty-auto-index-fund-review-performance-risk-explained-simply/": {
      "name": "Nippon India Nifty Auto Index Fund-Reg(G)",
      "category": "",
      "nav": "",
      "nav_date": "",
      "returns": {},
      "allocation": {},
      "risk_level": "",
      "risk_quants": {},
      "benchmark": "",
      "expense_ratio": ""
    },
    "nippon-india-nifty-bank-index-fund-review-performance-risk-explained-simply/": {
      "name": "Nippon India Nifty Bank Index Fund-Reg(G)",
      "category": "",
      "nav": "",
      "nav_date": "",
      "returns": {},
      "allocation": {},
      "risk_level": "",
      "risk_quants": {},
      "benchmark": "",
      "expense_ratio": ""
    },
    "nippon-india-nifty-india-manufacturing-index-fund-review-performance-metrics-risk-profile/": {
      "name": "Nippon India Nifty India Manufacturing Index Fund-Reg(G)",
      "category": "",
      "nav": "",
      "nav_date": "",
      "returns": {},
      "allocation": {},
      "risk_level": "",
      "risk_quants": {},
      "benchmark": "",
      "expense_ratio": ""
    },
    "nippon-india-nifty-it-index-fund-review-performance-metrics-risk-profile/": {
      "name": "Nippon India Nifty IT Index Fund-Reg(G)",
      "category": "",
      "nav": "",
      "nav_date": "",
      "returns": {},
      "allocation": {},
      "risk_level": "",
      "risk_quants": {},
      "benchmark": "",
      "expense_ratio": ""
    },
    "nippon-india-nifty-midcap-150-index-fund-review-performance-metrics-risk-profile/": {
      "name": "Nippon India Nifty Midcap 150 Index Fund-Reg(G)",
      "category": "",
      "nav": "",
      "nav_date": "",
      "returns": {},
      "allocation": {},
      "risk_level": "",
      "risk_quants": {},
      "benchmark": "",
      "expense_ratio": ""
    },
    "nippon-india-nifty-next-50-junior-bees-fof-review-performance-metrics-risk-profile/": {
      "name": "Nippon India Nifty Next 50 Junior BeES FoF-Reg(G)",
      "category": "",
      "nav": "",
      "nav_date": "",
      "returns": {},
      "allocation": {},
      "risk_level": "",
      "risk_quants": {},
      "benchmark": "",
      "expense_ratio": ""
    },
    "nippon-india-nifty-realty-index-fund-review-performance-metrics-risk-profile/": {
      "name": "Nippon India Nifty Realty Index Fund-Reg(G)",
      "category": "",
      "nav": "",
      "nav_date": "",
      "returns": {},
      "allocation": {},
      "risk_level": "",
      "risk_quants": {},
      "benchmark": "",
      "expense_ratio": ""
    },
    "nippon-india-nifty-smallcap-250-index-fund-review-performance-metrics-risk-profile/": {
      "name": "Nippon India Nifty Smallcap 250 Index Fund-Reg(G)",
      "category": "",
      "nav": "",
      "nav_date": "",
      "returns": {},
      "allocation": {},
      "risk_level": "",
      "risk_quants": {},
      "benchmark": "",
      "expense_ratio": ""
    },
    "nippon-india-pharma-fund-review-performance-metrics-risk-profile/": {
      "name": "Nippon India Pharma Fund(G)",
      "category": "",
      "nav": "",
      "nav_date": "",
      "returns": {},
      "allocation": {},
      "risk_level": "",
      "risk_quants": {},
      "benchmark": "",
      "expense_ratio": ""
    },
    "nippon-india-power-infra-fund-review-performance-metrics-risk-profile/": {
      "name": "Nippon India Power & Infra Fund(G)",
      "category": "",
      "nav": "",
      "nav_date": "",
      "returns": {},
      "allocation": {},
      "risk_level": "",
      "risk_quants": {},
      "benchmark": "",
      "expense_ratio": ""
    },
    "nippon-india-quant-fund-review-performance-metrics-risk-profile/": {
      "name": "Nippon India Quant Fund(G)",
      "category": "",
      "nav": "",
      "nav_date": "",
      "returns": {},
      "allocation": {},
      "risk_level": "",
      "risk_quants": {},
      "benchmark": "",
      "expense_ratio": ""
    },
    "nippon-india-silver-etf-fof-review-performance-metrics-risk-profile/": {
      "name": "Nippon India Silver ETF FOF-Reg(G)",
      "category": "",
      "nav": "",
      "nav_date": "",
      "returns": {},
      "allocation": {},
      "risk_level": "",
      "risk_quants": {},
      "benchmark": "",
      "expense_ratio": ""
    },
    "nippon-india-small-cap-fund-review-performance-metrics-risk-profile/": {
      "name": "Nippon India Small Cap Fund(G)",
      "category": "",
      "nav": "",
      "nav_date": "",
      "returns": {},
      "allocation": {},
      "risk_level": "",
      "risk_quants": {},
      "benchmark": "",
      "expense_ratio": ""
    },
    "nippon-india-taiwan-equity-fund-review-performance-metrics-risk-profile/": {
      "name": "Nippon India Taiwan Equity Fund-Reg(G)",
      "category": "",
      "nav": "",
      "nav_date": "",
      "returns": {},
      "allocation": {},
      "risk_level": "",
      "risk_quants": {},
      "benchmark": "",
      "expense_ratio": ""
    },
    "nippon-india-us-equity-opp-fund-review-performance-metrics-risk-profile/": {
      "name": "Nippon India US Equity Opp Fund(G)",
      "category": "",
      "nav": "",
      "nav_date": "",
      "returns": {},
      "allocation": {},
      "risk_level": "",
      "risk_quants": {},
      "benchmark": "",
      "expense_ratio": ""
    },
    "nippon-india-value-fund-review-performance-metrics-risk-profile/": {
      "name": "Nippon India Value Fund(G)",
      "category": "",
      "nav": "",
      "nav_date": "",
      "returns": {},
      "allocation": {},
      "risk_level": "",
      "risk_quants": {},
      "benchmark": "",
      "expense_ratio": ""
    },
    "nippon-india-vision-large-mid-cap-fund-review-performance-metrics-risk-profile/": {
      "name": "Nippon India Vision Large & Mid Cap Fund(G)",
      "category": "",
      "nav": "",
      "nav_date": "",
      "returns": {},
      "allocation": {},
      "risk_level": "",
      "risk_quants": {},
      "benchmark": "",
      "expense_ratio": ""
    }
  }
}